dld_array_generator
