Metadata-Version: 2.1
Name: dld-array-generator
Version: 1.0.3
Summary: Python package to generate parameterized DLD arrays.
Home-page: https://github.com/mkals/dld_array_generator
Author: Morten Kals
Author-email: dev@mkals.no
License: UNKNOWN
Platform: UNKNOWN
Classifier: Programming Language :: Python :: 3
Classifier: License :: OSI Approved :: MIT License
Classifier: Operating System :: OS Independent
Requires-Python: >=3.6
